auditlog/__init__.py
auditlog/admin.py
auditlog/apps.py
auditlog/compat.py
auditlog/diff.py
auditlog/filters.py
auditlog/middleware.py
auditlog/mixins.py
auditlog/models.py
auditlog/receivers.py
auditlog/registry.py
auditlog/utils.py
auditlog/management/__init__.py
auditlog/management/commands/__init__.py
auditlog/management/commands/auditlogflush.py
auditlog/migrations/0001_initial.py
auditlog/migrations/0002_auto_support_long_primary_keys.py
auditlog/migrations/0003_logentry_remote_addr.py
auditlog/migrations/0004_logentry_detailed_object_repr.py
auditlog/migrations/0005_logentry_additional_data_verbose_name.py
auditlog/migrations/0006_object_pk_index.py
auditlog/migrations/0007_object_pk_type.py
auditlog/migrations/__init__.py
auditlog3-1.0.1.dist-info/LICENSE
auditlog3-1.0.1.dist-info/METADATA
auditlog3-1.0.1.dist-info/WHEEL
auditlog3-1.0.1.dist-info/top_level.txt
auditlog3-1.0.1.dist-info/RECORD
